{
    "message": "",
    "result": {
        "sales_day": [
            {
                "name": "Lunes",
                "value": 140.55
            },
            {
                "name": "Martes",
                "value": 140.55
            },
            {
                "name": "Miércoles",
                "value": 140.55
            },
            {
                "name": "Jueves",
                "value": 140.55
            },
            {
                "name": "Viernes",
                "value": 140.55
            },
            {
                "name": "Sábado",
                "value": 140.55
            },
            {
                "name": "Domingo",
                "value": 140.55
            }
        ]
    }
}